[
  {
    "ContainingType": "NetCoreAPI.Controllers.ClienteController",
    "Method": "eliminarCliente",
    "RelativePath": "Cliente/eliminar",
    "HttpMethod": "POST",
    "IsController": true,
    "Order": 0,
    "Parameters": [
      {
        "Name": "cliente",
        "Type": "NetCoreAPI.Models.ClienteModel",
        "IsRequired": true
      }
    ],
    "ReturnTypes": []
  },
  {
    "ContainingType": "NetCoreAPI.Controllers.ClienteController",
    "Method": "guardarCliente",
    "RelativePath": "Cliente/guardar",
    "HttpMethod": "GET",
    "IsController": true,
    "Order": 0,
    "Parameters": [
      {
        "Name": "cliente",
        "Type": "NetCoreAPI.Models.ClienteModel",
        "IsRequired": true
      }
    ],
    "ReturnTypes": []
  },
  {
    "ContainingType": "NetCoreAPI.Controllers.ClienteController",
    "Method": "listarCliente",
    "RelativePath": "Cliente/listar",
    "HttpMethod": "GET",
    "IsController": true,
    "Order": 0,
    "Parameters": [],
    "ReturnTypes": []
  },
  {
    "ContainingType": "NetCoreAPI.Controllers.ClienteController",
    "Method": "listarClientexid",
    "RelativePath": "Cliente/listarxid",
    "HttpMethod": "GET",
    "IsController": true,
    "Order": 0,
    "Parameters": [
      {
        "Name": "_id",
        "Type": "System.String",
        "IsRequired": false
      }
    ],
    "ReturnTypes": []
  },
  {
    "ContainingType": "NetCoreAPI.Controllers.WeatherForecastController",
    "Method": "Get",
    "RelativePath": "WeatherForecast",
    "HttpMethod": "GET",
    "IsController": true,
    "Order": 0,
    "Parameters": [],
    "ReturnTypes": [
      {
        "Type": "System.Collections.Generic.IEnumerable\u00601[[NetCoreAPI.WeatherForecast, NetCoreAPI, Version=1.0.0.0, Culture=neutral, PublicKeyToken=null]]",
        "MediaTypes": [
          "text/plain",
          "application/json",
          "text/json"
        ],
        "StatusCode": 200
      }
    ]
  }
]